{
  "project_info": {
    "project_number": "401365642954",
    "firebase_url": "https://digital-diary-fyp.firebaseio.com",
    "project_id": "digital-diary-fyp",
    "storage_bucket": "digital-diary-fyp.appspot.com"
  },
  "client": [
    {
      "client_info": {
        "mobilesdk_app_id": "1:401365642954:android:536dbc87a6ac2dae2e8e33",
        "android_client_info": {
          "package_name": "com.digital_diary"
        }
      },
      "oauth_client": [
        {
          "client_id": "401365642954-u74fp36qfhobgr0qrp97vlmbbdvl3nfd.apps.googleusercontent.com",
          "client_type": 3
        }
      ],
      "api_key": [
        {
          "current_key": "AIzaSyCBis8K90cJV0AIeXYfvNIyVMWhgy1z2RA"
        }
      ],
      "services": {
        "appinvite_service": {
          "other_platform_oauth_client": [
            {
              "client_id": "401365642954-u74fp36qfhobgr0qrp97vlmbbdvl3nfd.apps.googleusercontent.com",
              "client_type": 3
            }
          ]
        }
      }
    }
  ],
  "configuration_version": "1"
}